emotion_detective/__init__.py
emotion_detective/data/__init__.py
emotion_detective/data/inference/__init__.py
emotion_detective/data/inference/data_ingestion.py
emotion_detective/data/inference/data_preprocessing.py
emotion_detective/data/training/__init__.py
emotion_detective/data/training/data_ingestion.py
emotion_detective/data/training/data_preprocessing.py
emotion_detective/logger/__init__.py
emotion_detective/logger/logger.py
emotion_detective/logs/__init__.py
emotion_detective/logs/emotion_detective.txt
emotion_detective/logs/error.log
emotion_detective/main.py
emotion_detective/models/__init__.py
emotion_detective/models/logs/emotion_detective.txt
emotion_detective/models/model_definitions.py
emotion_detective/models/model_evaluate.py
emotion_detective/models/model_predict.py
emotion_detective/models/model_saving.py
emotion_detective/models/model_training.py
emotion_detective/training.py
emotion_detective-1.3.8.dist-info/METADATA
emotion_detective-1.3.8.dist-info/WHEEL
emotion_detective-1.3.8.dist-info/RECORD
