Metadata-Version: 2.1
Name: emotion_detective
Version: 1.3.8
Summary: This package provides functions to analyze emotions in video or audio files. It offers a comprehensive set of tools to detect and analyze emotions at a sentence level, producing valuable insights into the emotion-content in videos and audios.
Author: Amy Suneeth, Martin Vladimirov, Andrea Tosheva, Kacper Janczyk, Rebecca Borski
Requires-Python: >=3.9,<4.0
Classifier: Programming Language :: Python :: 3
Classifier: Programming Language :: Python :: 3.9
Classifier: Programming Language :: Python :: 3.10
Classifier: Programming Language :: Python :: 3.11
Classifier: Programming Language :: Python :: 3.12
Requires-Dist: accelerate (>=0.20.1)
Requires-Dist: azure-ai-ml (>=1.17.0,<2.0.0)
Requires-Dist: azureml-core (>=1.56.0,<2.0.0)
Requires-Dist: azureml-fsspec (>=1.3.1,<2.0.0)
Requires-Dist: azureml-mlflow (>=1.56.0,<2.0.0)
Requires-Dist: colorama (>=0.4.6,<0.5.0)
Requires-Dist: datasets (>=2.20.0,<3.0.0)
Requires-Dist: fastapi (>=0.111.0)
Requires-Dist: gensim (>=4.3.2,<5.0.0)
Requires-Dist: h5py (>=3.11.0,<4.0.0)
Requires-Dist: imageio (==2.34.1)
Requires-Dist: imageio-ffmpeg (==0.4.9)
Requires-Dist: matplotlib (>=3.9.0,<4.0.0)
Requires-Dist: mlflow (>=2.13.2,<3.0.0)
Requires-Dist: moviepy (==1.0.3)
Requires-Dist: nltk (==3.8.1) ; sys_platform == "linux"
Requires-Dist: nltk (>=3.6.3,<4.0.0) ; sys_platform == "win32"
Requires-Dist: numpy (==1.23.2)
Requires-Dist: pandas (>=2.0.0,<3.0.0)
Requires-Dist: pydub (==0.25.1)
Requires-Dist: pyspellchecker (>=0.8.1,<0.9.0)
Requires-Dist: regex (==2024.5.10)
Requires-Dist: safetensors (==0.4.2)
Requires-Dist: scikit-learn (>=1.0,<2.0)
Requires-Dist: scipy (==1.12)
Requires-Dist: setuptools-rust (==1.9.0)
Requires-Dist: sphinx-rtd-theme (>=2.0.0,<3.0.0)
Requires-Dist: textblob (>=0.18.0.post0,<0.19.0)
Requires-Dist: tokenizers (==0.11.1) ; sys_platform == "linux"
Requires-Dist: tokenizers (==0.19) ; sys_platform == "win32"
Requires-Dist: torch (>=2.1.2,<3.0.0)
Requires-Dist: torchvision (>=0.16.2,<0.17.0)
Requires-Dist: transformers (>=4.30.0,<5.0.0)
Requires-Dist: typer (>=0.12.3)
Requires-Dist: uvicorn (>=0.22.0,<0.23.0)
Requires-Dist: wordninja (>=2.0.0,<3.0.0)
